{
  "project_info": {
    "project_number": "456337366080",
    "project_id": "lakeside-textbook-exchange",
    "storage_bucket": "lakeside-textbook-exchange.appspot.com"
  },
  "client": [
    {
      "client_info": {
        "mobilesdk_app_id": "1:456337366080:android:19bd807adcc355e26293a5",
        "android_client_info": {
          "package_name": "com.example.textbookexchange"
        }
      },
      "oauth_client": [
        {
          "client_id": "456337366080-7j1dacqh14k60j7n4ci5f7ss1fhfnbji.apps.googleusercontent.com",
          "client_type": 3
        }
      ],
      "api_key": [
        {
          "current_key": "AIzaSyCC2WSGiiI08d_Qd84df6J99EM5rBZqXlA"
        }
      ],
      "services": {
        "appinvite_service": {
          "other_platform_oauth_client": [
            {
              "client_id": "456337366080-7j1dacqh14k60j7n4ci5f7ss1fhfnbji.apps.googleusercontent.com",
              "client_type": 3
            }
          ]
        }
      }
    }
  ],
  "configuration_version": "1"
}